LICENSE
README.md
release.sh
setup.py
params/stog_amr_1.0.yaml
params/stog_amr_2.0.yaml
scripts/annotate_features.sh
scripts/compute_smatch.sh
scripts/download_artifacts.sh
scripts/eval_test.sh
scripts/postprocess_1.0.sh
scripts/postprocess_2.0.sh
scripts/prepare_data.sh
scripts/preprocess_1.0.sh
scripts/preprocess_2.0.sh
stog/__init__.py
stog/algorithms/__init__.py
stog/algorithms/dict_merge.py
stog/algorithms/maximum_spanning_tree.py
stog/commands/__init__.py
stog/commands/evaluate.py
stog/commands/predict.py
stog/commands/subcommand.py
stog/commands/train.py
stog/data/__init__.py
stog/data/dataset.py
stog/data/dataset_builder.py
stog/data/instance.py
stog/data/vocabulary.py
stog/data/dataset_readers/__init__.py
stog/data/dataset_readers/abstract_meaning_representation.py
stog/data/dataset_readers/dataset_reader.py
stog/data/dataset_readers/amr_parsing/__init__.py
stog/data/dataset_readers/amr_parsing/amr.py
stog/data/dataset_readers/amr_parsing/graph_repair.py
stog/data/dataset_readers/amr_parsing/io.py
stog/data/dataset_readers/amr_parsing/node_utils.py
stog/data/dataset_readers/amr_parsing/propbank_reader.py
stog/data/dataset_readers/amr_parsing/amr_concepts/__init__.py
stog/data/dataset_readers/amr_parsing/amr_concepts/date.py
stog/data/dataset_readers/amr_parsing/amr_concepts/entity.py
stog/data/dataset_readers/amr_parsing/amr_concepts/ordinal.py
stog/data/dataset_readers/amr_parsing/amr_concepts/polarity.py
stog/data/dataset_readers/amr_parsing/amr_concepts/polite.py
stog/data/dataset_readers/amr_parsing/amr_concepts/quantity.py
stog/data/dataset_readers/amr_parsing/amr_concepts/score.py
stog/data/dataset_readers/amr_parsing/amr_concepts/url.py
stog/data/dataset_readers/amr_parsing/postprocess/__init__.py
stog/data/dataset_readers/amr_parsing/postprocess/expander.py
stog/data/dataset_readers/amr_parsing/postprocess/node_restore.py
stog/data/dataset_readers/amr_parsing/postprocess/postprocess.py
unofficial_stog.egg-info/PKG-INFO
unofficial_stog.egg-info/SOURCES.txt
unofficial_stog.egg-info/dependency_links.txt
unofficial_stog.egg-info/requires.txt
unofficial_stog.egg-info/top_level.txt