Metadata-Version: 2.1
Name: unofficial-stog
Version: 0.0.21
Summary: Unofficial Package of AMR Parsing as Sequence-to-Graph Transduction
Home-page: https://github.com/sheng-z/stog
License: MIT
Keywords: corpus,machine-learning,NLU,NLP
Platform: UNKNOWN
Classifier: Intended Audience :: Science/Research
Classifier: Intended Audience :: Developers
Classifier: Development Status :: 3 - Alpha
Classifier: Operating System :: OS Independent
Classifier: Programming Language :: Python :: 3 :: Only
Classifier: Topic :: Scientific/Engineering :: Artificial Intelligence
Classifier: Topic :: Text Processing :: Linguistic
Requires-Python: >=3.6
